aws_cost_calculator_cli-2.9.0.dist-info/licenses/LICENSE
cost_calculator/__init__.py
cost_calculator/api_client.py
cost_calculator/cli.py
cost_calculator/cur.py
cost_calculator/dimensions.py
cost_calculator/drill.py
cost_calculator/executor.py
cost_calculator/forensics.py
cost_calculator/help_content.py
cost_calculator/monthly.py
cost_calculator/trends.py
aws_cost_calculator_cli-2.9.0.dist-info/METADATA
aws_cost_calculator_cli-2.9.0.dist-info/WHEEL
aws_cost_calculator_cli-2.9.0.dist-info/entry_points.txt
aws_cost_calculator_cli-2.9.0.dist-info/top_level.txt
aws_cost_calculator_cli-2.9.0.dist-info/RECORD
