Metadata-Version: 2.4
Name: aws-cost-calculator-cli
Version: 2.9.0
Summary: AWS Cost Calculator CLI - Calculate daily and annual AWS costs across multiple accounts
Home-page: https://github.com/trilogy-group/aws-cost-calculator
Author: Cost Optimization Team
Author-email: 
Project-URL: Documentation, https://github.com/trilogy-group/aws-cost-calculator/blob/main/README.md
Keywords: aws cost calculator billing optimization cloud
Classifier: Development Status :: 4 - Beta
Classifier: Intended Audience :: Developers
Classifier: Intended Audience :: System Administrators
Classifier: Topic :: System :: Monitoring
Classifier: Topic :: Utilities
Classifier: License :: OSI Approved :: MIT License
Classifier: Programming Language :: Python :: 3
Classifier: Programming Language :: Python :: 3.8
Classifier: Programming Language :: Python :: 3.9
Classifier: Programming Language :: Python :: 3.10
Classifier: Programming Language :: Python :: 3.11
Requires-Python: >=3.8
License-File: LICENSE
Requires-Dist: click>=8.0.0
Requires-Dist: boto3>=1.26.0
Requires-Dist: requests>=2.28.0
Dynamic: author
Dynamic: classifier
Dynamic: description
Dynamic: description-content-type
Dynamic: home-page
Dynamic: keywords
Dynamic: license-file
Dynamic: project-url
Dynamic: requires-dist
Dynamic: requires-python
Dynamic: summary
